{
  "main": {
    "id": "8e3f4e74d683475d",
    "type": "split",
    "children": [
      {
        "id": "afaf36a1bbc846b2",
        "type": "tabs",
        "children": [
          {
            "id": "8590742af00ea539",
            "type": "leaf",
            "state": {
              "type": "markdown",
              "state": {
                "file": "Desigualdad de Cauchy.md",
                "mode": "source",
                "source": false
              }
            }
          },
          {
            "id": "b9cd970a3365f38c",
            "type": "leaf",
            "state": {
              "type": "markdown",
              "state": {
                "file": "Teorema de Louville.md",
                "mode": "source",
                "source": false
              }
            }
          },
          {
            "id": "e33c84fbbd27199c",
            "type": "leaf",
            "state": {
              "type": "canvas",
              "state": {
                "file": "Holomorfa implica Analítica.canvas",
                "viewState": {
                  "x": 159.6146247536955,
                  "y": 490.2783059387988,
                  "zoom": -1.4
                }
              }
            }
          },
          {
            "id": "035bd37e1d97a87f",
            "type": "leaf",
            "state": {
              "type": "markdown",
              "state": {
                "file": "Holomorfa implica Analítica.md",
                "mode": "source",
                "source": false
              }
            }
          },
          {
            "id": "a416465efc951f87",
            "type": "leaf",
            "state": {
              "type": "markdown",
              "state": {
                "file": "Holomorfa implica Analítica.md",
                "mode": "source",
                "source": false
              }
            }
          },
          {
            "id": "32e892a6b425e0e1",
            "type": "leaf",
            "state": {
              "type": "markdown",
              "state": {
                "file": "Yoga de funciones analíticas.md",
                "mode": "source",
                "source": false
              }
            }
          },
          {
            "id": "3ff629d813c4f5fd",
            "type": "leaf",
            "state": {
              "type": "graph",
              "state": {}
            }
          }
        ],
        "currentTab": 1
      },
      {
        "id": "2cdf3677873e5e10",
        "type": "tabs",
        "children": [
          {
            "id": "396d60bec3e246f0",
            "type": "leaf",
            "state": {
              "type": "markdown",
              "state": {
                "file": "Temas complejo.md",
                "mode": "source",
                "source": false
              }
            }
          }
        ]
      }
    ],
    "direction": "vertical"
  },
  "left": {
    "id": "f75a68c430c7f8a9",
    "type": "split",
    "children": [
      {
        "id": "c129021ddcc47c8d",
        "type": "tabs",
        "children": [
          {
            "id": "144643a686d216ce",
            "type": "leaf",
            "state": {
              "type": "file-explorer",
              "state": {
                "sortOrder": "alphabetical"
              }
            }
          },
          {
            "id": "d69789eb6af63c5d",
            "type": "leaf",
            "state": {
              "type": "search",
              "state": {
                "query": "",
                "matchingCase": false,
                "explainSearch": false,
                "collapseAll": false,
                "extraContext": false,
                "sortOrder": "alphabetical"
              }
            }
          },
          {
            "id": "f4892ceb9eba0bd7",
            "type": "leaf",
            "state": {
              "type": "bookmarks",
              "state": {}
            }
          }
        ],
        "currentTab": 1
      }
    ],
    "direction": "horizontal",
    "width": 200,
    "collapsed": true
  },
  "right": {
    "id": "bc05b07eafa9dc05",
    "type": "split",
    "children": [
      {
        "id": "7ea55af62362fc41",
        "type": "tabs",
        "children": [
          {
            "id": "bf2e34d49d86d8cf",
            "type": "leaf",
            "state": {
              "type": "tag",
              "state": {
                "sortOrder": "frequency",
                "useHierarchy": true
              }
            }
          },
          {
            "id": "7acc1e960529fc21",
            "type": "leaf",
            "state": {
              "type": "calendar",
              "state": {}
            }
          },
          {
            "id": "6b45dc4e195a2608",
            "type": "leaf",
            "state": {
              "type": "backlink",
              "state": {
                "file": "Teorema de Louville.md",
                "collapseAll": false,
                "extraContext": false,
                "sortOrder": "alphabetical",
                "showSearch": false,
                "searchQuery": "",
                "backlinkCollapsed": false,
                "unlinkedCollapsed": false
              }
            }
          },
          {
            "id": "cd70a452e3661dd0",
            "type": "leaf",
            "state": {
              "type": "outgoing-link",
              "state": {
                "file": "Teorema de Louville.md",
                "linksCollapsed": false,
                "unlinkedCollapsed": true
              }
            }
          },
          {
            "id": "7a659b3cc5c5bb25",
            "type": "leaf",
            "state": {
              "type": "outline",
              "state": {
                "file": "Teorema de Louville.md"
              }
            }
          },
          {
            "id": "5b57a87fc1922f37",
            "type": "leaf",
            "state": {
              "type": "advanced-tables-toolbar",
              "state": {}
            }
          },
          {
            "id": "269538021a54ffdc",
            "type": "leaf",
            "state": {
              "type": "all-properties",
              "state": {
                "sortOrder": "frequency",
                "showSearch": false,
                "searchQuery": ""
              }
            }
          }
        ],
        "currentTab": 4
      }
    ],
    "direction": "horizontal",
    "width": 200,
    "collapsed": true
  },
  "left-ribbon": {
    "hiddenItems": {
      "switcher:Open quick switcher": false,
      "graph:Open graph view": false,
      "canvas:Create new canvas": false,
      "daily-notes:Open today's daily note": false,
      "templates:Insert template": false,
      "command-palette:Open command palette": false,
      "random-note:Open random note": false,
      "obsidian-excalidraw-plugin:Create new drawing": false,
      "table-editor-obsidian:Advanced Tables Toolbar": false,
      "templater-obsidian:Templater": false,
      "obsidian-advanced-slides:Show Slide Preview": false,
      "obsidian-statusbar-pomo:Start pomodoro": false
    }
  },
  "active": "b9cd970a3365f38c",
  "lastOpenFiles": [
    "Desigualdad de Cauchy.md",
    "Temas complejo.md",
    "Holomorfa implica Analítica.md",
    "Holomorfa implica Analítica.canvas",
    "Teorema de Louville.md",
    "Función entera.md",
    "Fórmula de Cauchy.md",
    "Yoga de funciones analíticas.md",
    "Integral compleja de la función inversa.md",
    "Yoga de integración compleja.md",
    "fórmula de la serie geométrica.md",
    "Teorema de Cauchy segunda versión.md",
    "Teorema de Cauchy Primera versión.md",
    "Excalidraw/Teorema de Cauchy 2024-02-29 00.41.34.excalidraw.md",
    "Excalidraw/Teorema de Cauchy segunda versión 2024-02-29 16.44.15.excalidraw.md",
    "Excalidraw/Teorema de Cauchy 2024-02-29 01.34.35.excalidraw.md",
    "Untitled 8.md",
    "snippets.md",
    "Excalidraw/Teorema de Cauchy 2024-02-28 21.20.14.excalidraw.md",
    "Excalidraw/Yoga de integración compleja 2024-02-28 20.38.58.excalidraw.md",
    "Integración de funciones complejas.md",
    "Ecuaciones de Cauchy-Riemann.md",
    "Análisis complejo.md",
    "Análisis de métodos numéricos.md",
    "Cálculo numérico.md",
    "Convergencia de los métodos de cuadratura.md",
    "Elementos de cálculo numérico.canvas",
    "Libros/Duran_Lassalle_Rossi.pdf",
    "Libros/applied_cateogry_theory.pdf",
    "Duran_Lassalle_Rossi.pdf",
    "Libros/hatcher.pdf",
    "barcodes_ghrist.pdf",
    "EATchapter4_ghrist.pdf",
    "Libros/aluffi.pdf",
    "Libros/Algebra 2/Notas8.pdf",
    "Libros/Algebra 2/Notas15.pdf",
    "Libros/Algebra 2/Notas17.pdf",
    "export/Clase Fourier/Fuentes/Formula Fourier.png",
    "export/Clase Fourier/Fuentes/output.png",
    "export/Clase Fourier/Fuentes/coeficientes_matriz.png",
    "export/Clase Fourier/Fuentes/Solucionperiodica.png",
    "export/Clase Fourier/plugin/chalkboard/img/blackboard.png",
    "export/Clase Fourier/plugin/chalkboard/img/boardmarker-black.png",
    "export/Clase Fourier/plugin/chalkboard/img/boardmarker-blue.png",
    "export/Clase Fourier/plugin/chalkboard/img/boardmarker-green.png",
    "export/Clase Fourier/plugin/chalkboard/img/boardmarker-orange.png",
    "export/Clase Fourier/plugin/chalkboard/img/boardmarker-purple.png"
  ]
}